[
  {
    "userID": "100067508386723",
    "name": "Phạm Hữu Tài",
    "count": 66,
    "rank": 1
  },
  {
    "userID": "100027187763993",
    "name": "Vũ Thành Trung",
    "count": 50,
    "rank": 2
  },
  {
    "userID": "61554533647809",
    "name": "Vũ Thành Trung",
    "count": 25,
    "rank": 3
  },
  {
    "userID": "100090880981407",
    "name": "Ngọc Mỹ",
    "count": 24,
    "rank": 4
  },
  {
    "userID": "100075940538217",
    "name": "Nguyen Huu Trin",
    "count": 23,
    "rank": 5
  },
  {
    "userID": "100087126503731",
    "name": "Uchıha Obito",
    "count": 16,
    "rank": 6
  },
  {
    "userID": "61554857334283",
    "name": "Nguyễn Hoàng Hữu Trí",
    "count": 2,
    "rank": 7
  },
  {
    "userID": "100021378861577",
    "name": "Lê Văn Phước",
    "count": 0,
    "rank": 8
  },
  {
    "userID": "100022448225417",
    "name": "ミン ドゥ",
    "count": 0,
    "rank": 9
  },
  {
    "userID": "100023419935399",
    "name": "Người dùng Facebook",
    "count": 0,
    "rank": 10
  },
  {
    "userID": "100058410016944",
    "name": "Vũ Luân",
    "count": 0,
    "rank": 11
  },
  {
    "userID": "100062172456295",
    "name": "Thảo Nguyên",
    "count": 0,
    "rank": 12
  },
  {
    "userID": "100079274402645",
    "name": "Nguyễn Trọng Hiếu",
    "count": 0,
    "rank": 13
  },
  {
    "userID": "100086502717517",
    "name": "Nguyễn Tùng",
    "count": 0,
    "rank": 14
  }
]
